README.md
setup.py
firebase_dynamic_links/__init__.py
firebase_dynamic_links/dynamic_links.py
py_firebase_dynamic_links.egg-info/PKG-INFO
py_firebase_dynamic_links.egg-info/SOURCES.txt
py_firebase_dynamic_links.egg-info/dependency_links.txt
py_firebase_dynamic_links.egg-info/requires.txt
py_firebase_dynamic_links.egg-info/top_level.txt