Metadata-Version: 2.1
Name: py-firebase-dynamic-links
Version: 1.0.0
Summary: Python client for Firebase Dynamic Links API
Home-page: https://github.com/dpeite/py-firebase-dynamic-links
Author: Daniel Vilar Peiteado
Author-email: danielvilar2@gmail.com
Maintainer: Daniel Vilar Peiteado
Maintainer-email: danielvilar2@gmail.com
License: UNKNOWN
Project-URL: Bug Reports, https://github.com/dpeite/py-firebase-dynamic-links/issues
Project-URL: Source, https://github.com/dpeite/py-firebase-dynamic-links
Keywords: firebase,dynamic links,url shortener
Platform: UNKNOWN
Classifier: Programming Language :: Python :: 3
Classifier: License :: OSI Approved :: MIT License
Classifier: Operating System :: OS Independent
Classifier: Development Status :: 5 - Production/Stable
Classifier: Intended Audience :: Developers
Classifier: Topic :: Software Development :: Libraries :: Python Modules
